stips/__init__.py
stips/conftest.py
stips/astro_image/__init__.py
stips/astro_image/astro_image.py
stips/astro_image/tests/__init__.py
stips/astro_image/tests/test_AstroImage.py
stips/astro_image/tests/test_header.py
stips/astro_image/tests/test_wcs.py
stips/data/CreateIsochroneGrid.py
stips/data/CreatePhoenixGrid.py
stips/data/__init__.py
stips/data/psf_WFI_2.0.0_F129_wfi01.fits
stips/data/stips_config.yaml
stips/errors/__init__.py
stips/errors/make_cosmic_ray.py
stips/instruments/__init__.py
stips/instruments/instrument.py
stips/instruments/roman_instrument.py
stips/instruments/wfi.py
stips/observation_module/__init__.py
stips/observation_module/observation_module.py
stips/scene_module/__init__.py
stips/scene_module/convert_units.py
stips/scene_module/scene_module.py
stips/stellar_module/__init__.py
stips/stellar_module/star_generator.py
stips/tests/__init__.py
stips/utilities/DataTable.py
stips/utilities/__init__.py
stips/utilities/makePSF.py
stips/utilities/testing.py
stips/utilities/utilities.py
stips/utilities/tests/test_config.py
stips/utilities/tests/test_makePSF.py
stips-2.3.dist-info/METADATA
stips-2.3.dist-info/WHEEL
stips-2.3.dist-info/top_level.txt
stips-2.3.dist-info/RECORD
