Metadata-Version: 2.4
Name: stips
Version: 2.3
Summary: STIPS is the Space Telescope Imaging Product Simulator.
Home-page: https://github.com/spacetelescope/STScI-STIPS
Author: Space Telescope Science Institute
Author-email: york@stsci.edu
License: BSD 3-Clause
Requires-Dist: astropy
Requires-Dist: numpy
Requires-Dist: scipy
Requires-Dist: photutils
Requires-Dist: synphot>=1.1.1
Requires-Dist: stsynphot>=1.1.0
Requires-Dist: stpsf>=2.0.0
Requires-Dist: pandeia.engine>=2024.12
Requires-Dist: montage-wrapper
Requires-Dist: pyyaml
Requires-Dist: soc_roman_tools
